tensorrt_dispatch_bindings/__init__.py
tensorrt_dispatch_bindings/tensorrt_dispatch.cp311-win_amd64.pyd
tensorrt_dispatch_bindings/plugin/__init__.py
tensorrt_dispatch_bindings/plugin/_autotune.py
tensorrt_dispatch_bindings/plugin/_export.py
tensorrt_dispatch_bindings/plugin/_lib.py
tensorrt_dispatch_bindings/plugin/_plugin_class.py
tensorrt_dispatch_bindings/plugin/_tensor.py
tensorrt_dispatch_bindings/plugin/_top_level.py
tensorrt_dispatch_bindings/plugin/_utils.py
tensorrt_dispatch_bindings/plugin/_validate.py
tensorrt_dispatch_cu12_bindings-10.15.1.29.dist-info/LICENSE.txt
tensorrt_dispatch_cu12_bindings-10.15.1.29.dist-info/METADATA
tensorrt_dispatch_cu12_bindings-10.15.1.29.dist-info/WHEEL
tensorrt_dispatch_cu12_bindings-10.15.1.29.dist-info/top_level.txt
tensorrt_dispatch_cu12_bindings-10.15.1.29.dist-info/zip-safe
tensorrt_dispatch_cu12_bindings-10.15.1.29.dist-info/RECORD
